tkshadowfy/__init__.py
tkshadowfy/shadow.py
tkshadowfy-1.0.0.dist-info/LICENSE
tkshadowfy-1.0.0.dist-info/METADATA
tkshadowfy-1.0.0.dist-info/WHEEL
tkshadowfy-1.0.0.dist-info/top_level.txt
tkshadowfy-1.0.0.dist-info/RECORD
