Metadata-Version: 2.1
Name: tkshadowfy
Version: 1.0.0
Summary: A library for adding shadow effects to Tkinter widgets
Home-page: https://github.com/nakxa/tkshadowfy
Author: Nakxa
Classifier: Programming Language :: Python :: 3
Classifier: License :: OSI Approved :: MIT License
Classifier: Operating System :: OS Independent
License-File: LICENSE
